{
    "version": "1.0.0",
    "summary": "An Elm client for the STOMP protocol.",
    "repository": "https://github.com/insurello/elm-stomp.git",
    "license": "MIT",
    "source-directories": [
        "src"
    ],
    "exposed-modules": [
        "Stomp.Client",
        "Stomp.Message",
        "Stomp.Proc",
        "Stomp.Subscription"
    ],
    "dependencies": {
        "elm-lang/websocket": "1.0.2 <= v < 2.0.0",
        "elm-lang/core": "5.1.1 <= v < 6.0.0"
    },
    "elm-version": "0.18.0 <= v < 0.19.0"
}
